gptsummary-0.0.13.dist-info/METADATA
gptsummary-0.0.13.dist-info/RECORD
gptsummary-0.0.13.dist-info/top_level.txt
gptsummary-0.0.13.dist-info/WHEEL
gptsummary/gptsummary.pyi
gptsummary/gptsummary.cpython-310-x86_64-linux-gnu.so
gptsummary/__init__.py
gptsummary/gptsummary.c
