Metadata-Version: 2.1
Name: gptsummary
Version: 0.0.13
Summary: AI-Powered Summary Tools
Author: Ainancer
Classifier: Programming Language :: Python :: 3
Classifier: License :: OSI Approved :: MIT License
Classifier: Operating System :: OS Independent
Requires-Python: >=3
Requires-Dist: openai >=1.14.3
